{
  "splitter": "뉴스",
  "split_conditions": [
    {
      "code": "종결어",
      "use_public_validation": "N",
      "split_position": "B",
      "value": ["종결어1", "종결어2"],
      "validations": [
        {
          "match_flag": "N",
          "compare_position": "B",
          "value": ["연결어1", "연결어2"]
        },
        {
          "match_flag": "Y",
          "compare_position": "F",
          "value": ["말머리기호"]
        }
      ]
    },
    {
      "code": "숫자 인덱스",
      "use_public_validation": "N",
      "split_position": "F",
      "value": ["숫자 인덱스1", "숫자_인덱스2"],
      "validations": [
        {
          "match_flag": "N",
          "compare_position": "B",
          "value": ["연결어1", "연결어2"]
        },
        {
          "match_flag": "Y",
          "compare_position": "F",
          "value": ["말머리기호"]
        }
      ]
    }
  ]
}

